{"guildID":"65c4ab8f402b6335686f54b9","name":"HK","owner":"64f34fb5de8ff0276ff9995d","status":"OPEN","statusInfo":{"id":1,"isActive":true,"autoJoin":true,"allowJoin":true},"numMembers":50,"numMembersPending":0,"maximumMembers":50,"tagline":"{\"Tagline\":\"GahNw7tn6R Day1 4k\",\"Symbol\":{\"Layers\":[\"Colour_03_Red\",\"Pattern_10\",\"Shield_14\",\"Icon_20_Sub\"]},\"MinBadge\":{\"id\":\"no_badge\",\"type\":\"WORLD\",\"cc\":\"\",\"rank\":-1,\"minRank\":-1,\"maxRank\":-1,\"score\":0,\"count\":0}}","full":true,"lastUpdated":1776260451445,"shortcode":"MDZMEXOG","activityRating":-1,"safeName":"HK","chatEnabled":true}