{"guildID":"5c3c3cfb03fcd3963db944f4","name":"96Z28","owner":"5b93a58091c282a81cc21ae3","status":"FILTERED","statusInfo":{"id":2,"isActive":true,"autoJoin":false,"allowJoin":true},"numMembers":12,"numMembersPending":0,"maximumMembers":50,"tagline":"{\"Tagline\":\"discord.gg/Cs3Zxr\",\"Symbol\":{\"Layers\":[\"Colour_06_DarkBlue\",\"Pattern_15\",\"Shield_02\",\"Icon_19_Buccaneer\"]},\"MinBadge\":{\"id\":\"silvergold\",\"type\":\"WORLD\",\"cc\":\"\",\"rank\":-1,\"minRank\":100,\"maxRank\":999,\"score\":0,\"count\":0}}","full":false,"lastUpdated":1585747913815,"shortcode":"NONE","activityRating":-1,"safeName":"NONE","chatEnabled":false}