{"guildID":"5b2a90fc6765406125a8b9a7","name":"Brown  Town","owner":"5cf7277bca4209d623a62c61","status":"FILTERED","statusInfo":{"id":2,"isActive":true,"autoJoin":false,"allowJoin":true},"numMembers":1,"numMembersPending":49,"maximumMembers":50,"tagline":"{\"Tagline\":\"Bob quit 11 days \",\"Symbol\":{\"Layers\":[\"Colour_12_Orange\",\"Pattern_10\",\"Shield_06\",\"Icon_04_Sungod\"]}}","full":false,"lastUpdated":1563087438606,"shortcode":"NONE","activityRating":-1,"safeName":"NONE","chatEnabled":false}