{"guildID":"590d14676bda8f160a49324f","name":"We Have Real Jobs!","owner":"55c59fc0bda8dec311fe80c9","status":"OPEN","statusInfo":{"id":1,"isActive":true,"autoJoin":true,"allowJoin":true},"numMembers":42,"numMembersPending":0,"maximumMembers":50,"tagline":"{\"Tagline\":\"under 50=kicked. have fun!\",\"Symbol\":{\"Layers\":[\"Colour_02_Grey\",\"Pattern_12\",\"Shield_09\",\"Icon_09_Darts\"]},\"MinBadge\":{\"id\":\"bronzex1\",\"type\":\"WORLD\",\"cc\":\"\",\"rank\":-1,\"minRank\":25000,\"maxRank\":49999,\"score\":0,\"count\":0}}","full":false,"lastUpdated":1505944159885,"shortcode":"NONE","activityRating":-1,"safeName":"NONE","chatEnabled":false}