{"guildID":"5d4871d6a318e317558a9ed4","name":"Supremacy ","owner":"5a163bc0c97a2dfd6ce9c903","status":"FILTERED","statusInfo":{"id":2,"isActive":true,"autoJoin":false,"allowJoin":true},"numMembers":34,"numMembersPending":0,"maximumMembers":50,"tagline":"{\"Tagline\":\"One for all, all for chiefs\",\"Symbol\":{\"Layers\":[\"Colour_02_Grey\",\"Pattern_07\",\"Shield_12\",\"Icon_17_TechTerror\"]},\"MinBadge\":{\"id\":\"\",\"type\":\"\",\"cc\":\"\",\"rank\":-1,\"minRank\":-1,\"maxRank\":-1,\"score\":0,\"count\":0}}","full":false,"lastUpdated":1565693493747,"shortcode":"NONE","activityRating":-1,"safeName":"NONE","chatEnabled":false}