{"guildID":"5d183e5ea7eeaee61b88ec1b","name":"Orange Juice ","owner":"5f1348589497cd1a1a104473","status":"FILTERED","statusInfo":{"id":2,"isActive":true,"autoJoin":false,"allowJoin":true},"numMembers":1,"numMembersPending":49,"maximumMembers":50,"tagline":"{\"Tagline\":\"First\",\"Symbol\":{\"Layers\":[\"Colour_02_Grey\",\"Pattern_10\",\"Shield_07\",\"Icon_02_Regen\"]},\"MinBadge\":{\"id\":\"no_badge\",\"type\":\"WORLD\",\"cc\":\"\",\"rank\":-1,\"minRank\":-1,\"maxRank\":-1,\"score\":0,\"count\":0}}","full":false,"lastUpdated":1599517054693,"shortcode":"NONE","activityRating":-1,"safeName":"NONE","chatEnabled":false}