{"version":1,"":{"FBID":"","GCID":"","GPID":"","STID":"","NKID":"5ff2b71ec0e0a718e62e4438","Name":"ForthHealer8","CountryCode":"US","Version":61500,"MatchmakingVersion":727,"Avatar":0,"Wins":204,"WinsCard":0,"WinsStandard":204,"Losses":304,"LossesCard":3,"LossesStandard":301,"TournamentWins":0,"TournamentWinsCard":0,"TournamentWinsStandard":0,"TournamentLosses":1,"TournamentLossesCard":0,"TournamentLossesStandard":1,"WholeTournamentWins":0,"WholeTournamentWinsCard":0,"WholeTournamentWinsStandard":0,"WholeTournamentLosses":1,"WholeTournamentLossesCard":0,"WholeTournamentLossesStandard":1,"CurrentWinStreak":0,"BestWinStreak":6,"Battlescore":2385,"MedallionsCurrent":4320,"MedallionWinsTotal":22634,"MedallionWinsWeekly":0,"CurrentLeaderboard":"WeeklyMedallions:367","Badges":[{"id":"bronzex1","type":"WORLD","cc":"","rank":34319,"minRank":-1,"maxRank":-1,"score":3950,"count":3}],"FeaturedBadge":{"id":"","type":"","cc":"","rank":-1,"minRank":-1,"maxRank":-1,"score":0,"count":0},"UseSocialAvatar":true,"GuildID":"61a4eff88a0af9597f60cccf"}}