{"version":1,"":{"FBID":"","GCID":"","GPID":"","STID":"","NKID":"5f33142fb2185917f2e8c35e","Name":"TooDrunkToWin","CountryCode":"US","Version":62303,"MatchmakingVersion":738,"Avatar":0,"Wins":1347,"WinsCard":38,"WinsStandard":1309,"Losses":884,"LossesCard":33,"LossesStandard":851,"TournamentWins":0,"TournamentWinsCard":0,"TournamentWinsStandard":0,"TournamentLosses":0,"TournamentLossesCard":0,"TournamentLossesStandard":0,"WholeTournamentWins":0,"WholeTournamentWinsCard":0,"WholeTournamentWinsStandard":0,"WholeTournamentLosses":0,"WholeTournamentLossesCard":0,"WholeTournamentLossesStandard":0,"CurrentWinStreak":6,"BestWinStreak":32,"Battlescore":143637,"MedallionsCurrent":5690466,"MedallionWinsTotal":157244761,"MedallionWinsWeekly":80000,"CurrentLeaderboard":"WeeklyMedallions:569","Badges":[{"id":"gold_diamond_prestige","type":"LADDER_RATING","cc":"","rank":38,"minRank":-1,"maxRank":-1,"score":14320000,"count":3},{"id":"gold_prestige","type":"LADDER_RATING","cc":"","rank":121,"minRank":-1,"maxRank":-1,"score":4610000,"count":33},{"id":"silver_gold_prestige","type":"LADDER_RATING","cc":"","rank":1123,"minRank":-1,"maxRank":-1,"score":409000,"count":6},{"id":"silver_prestige","type":"LADDER_RATING","cc":"","rank":2779,"minRank":-1,"maxRank":-1,"score":156600,"count":4},{"id":"bronze_silver_prestige","type":"LADDER_RATING","cc":"","rank":5541,"minRank":-1,"maxRank":-1,"score":46000,"count":2},{"id":"bronze_prestige","type":"LADDER_RATING","cc":"","rank":12260,"minRank":-1,"maxRank":-1,"score":17000,"count":2},{"id":"gold","type":"WORLD","cc":"","rank":27,"minRank":-1,"maxRank":-1,"score":4624000,"count":9},{"id":"silvergold","type":"WORLD","cc":"","rank":101,"minRank":-1,"maxRank":-1,"score":2680600,"count":119},{"id":"silverx2","type":"WORLD","cc":"","rank":1007,"minRank":-1,"maxRank":-1,"score":344000,"count":60},{"id":"silverx1","type":"WORLD","cc":"","rank":10103,"minRank":-1,"maxRank":-1,"score":21600,"count":12},{"id":"bronzex1","type":"WORLD","cc":"","rank":25161,"minRank":-1,"maxRank":-1,"score":5000,"count":13}],"FeaturedBadge":{"id":"gold_diamond_prestige","type":"LADDER_RATING","cc":"","rank":65,"minRank":-1,"maxRank":-1,"score":11815000,"count":1},"UseSocialAvatar":true,"GuildID":"654337dd6dbae5fd9de463f7"}}